datacollective/__init__.py
datacollective/api_utils.py
datacollective/dataset_loading_scripts/README.md
datacollective/dataset_loading_scripts/__init__.py
datacollective/dataset_loading_scripts/common_voice.py
datacollective/dataset_loading_scripts/registry.py
datacollective/datasets.py
datacollective-0.2.0.dist-info/licenses/LICENSE
datacollective-0.2.0.dist-info/WHEEL
datacollective-0.2.0.dist-info/entry_points.txt
datacollective-0.2.0.dist-info/METADATA
datacollective-0.2.0.dist-info/RECORD
