Metadata-Version: 2.4
Name: datacollective
Version: 0.2.0
Summary: A Python package for interfacing with the Mozilla Data Collective's API
Author: Mozilla Data Collective
Author-email: Mozilla Data Collective <mozilladatacollective@mozillafoundation.org>
License-Expression: MPL-2.0
License-File: LICENSE
Classifier: Programming Language :: Python :: 3
Classifier: Operating System :: OS Independent
Requires-Dist: fox-progress-bar>=0.1.1
Requires-Dist: pandas>=2.0.0
Requires-Dist: python-dotenv>=1.0.0
Requires-Dist: requests>=2.32.5
Requires-Dist: pytest>=7.0.0 ; extra == 'dev'
Requires-Dist: pytest-cov>=4.0.0 ; extra == 'dev'
Requires-Dist: pre-commit>=3.0.0 ; extra == 'dev'
Requires-Dist: bump2version>=1.0.0 ; extra == 'dev'
Requires-Dist: mkdocs ; extra == 'docs'
Requires-Dist: mkdocs-material ; extra == 'docs'
Requires-Dist: mkdocstrings-python ; extra == 'docs'
Requires-Python: >=3.11
Project-URL: Documentation, https://Mozilla-Data-Collective.github.io/datacollective-python/
Project-URL: Homepage, https://github.com/Mozilla-Data-Collective/datacollective-python
Project-URL: Issues, https://github.com/Mozilla-Data-Collective/datacollective-python/issues
Provides-Extra: dev
Provides-Extra: docs
